[{"VOCA":"affluent","SCRIPT":"부유한, 풍족한"},
{"VOCA":"aggravate","SCRIPT":"악화시키다"},
{"VOCA":"cling to","SCRIPT":"달라붙다, 고수하다"},
{"VOCA":"craft","SCRIPT":"솜씨있게 만들다"},
{"VOCA":"crest","SCRIPT":"정상"},
{"VOCA":"critic","SCRIPT":" 비평가"},
{"VOCA":"cross-hatching","SCRIPT":"음영"},
{"VOCA":"decimate","SCRIPT":"많은 사람을 죽이다"},
{"VOCA":"disciple","SCRIPT":" 제자"},
{"VOCA":"disclose","SCRIPT":" (사실 등을) 밝히다"},
{"VOCA":"disposition","SCRIPT":"성질, 기질"},
{"VOCA":"dissimilar","SCRIPT":"다른"},
{"VOCA":"dominant","SCRIPT":"우세한"},
{"VOCA":"effect","SCRIPT":"결과"},
{"VOCA":"effect","SCRIPT":"영향"},
{"VOCA":"enhance","SCRIPT":"향상시키다, 개선하다"},
{"VOCA":"enunciate","SCRIPT":"분명하게 발음하다"},
{"VOCA":"eradicate","SCRIPT":" 근절하다"},
{"VOCA":"harsh","SCRIPT":" 가혹한"},
{"VOCA":"heritage","SCRIPT":"전통, 유산"},
{"VOCA":"inappropriate","SCRIPT":"부적당한"},
{"VOCA":"insolent","SCRIPT":"무례한"},
{"VOCA":"jeopardy","SCRIPT":" 위험"},
{"VOCA":"luxury","SCRIPT":"사치"},
{"VOCA":"manipulate","SCRIPT":"조종하다, 다루다"},
{"VOCA":"mock","SCRIPT":" 조롱하다"},
{"VOCA":"precious","SCRIPT":" 귀중한"},
{"VOCA":"regard","SCRIPT":"관심"},
{"VOCA":"regard","SCRIPT":"호감, 존경"},
{"VOCA":"return","SCRIPT":"되돌아가다"},
{"VOCA":"set","SCRIPT":"~을 놓다"},
{"VOCA":"spacious","SCRIPT":" 넓은"},
{"VOCA":"spectator","SCRIPT":"구경꾼"},
{"VOCA":"strict","SCRIPT":" 엄격한"},
{"VOCA":"swift","SCRIPT":" 빠른"},
{"VOCA":"synchronize","SCRIPT":"동시에 일어나다"},
{"VOCA":"throughout","SCRIPT":"~의 도처에"},
{"VOCA":"undermine","SCRIPT":" 약화시키다"},
{"VOCA":"upset","SCRIPT":" 당황하게 하다"},
{"VOCA":"upset","SCRIPT":" 뒤엎다, 정복하다"},
{"VOCA":"virtuous","SCRIPT":"덕 있는"},
{"VOCA":"withdraw","SCRIPT":" 물러나다"},
{"VOCA":"worship","SCRIPT":" 숭배하다"},
{"VOCA":"wrangle","SCRIPT":"논쟁하다"},
{"VOCA":"wrangle","SCRIPT":"말다툼하다"}]
